client/__init__.py
ocfworker-0.0.3.dist-info/METADATA
ocfworker-0.0.3.dist-info/WHEEL
ocfworker-0.0.3.dist-info/top_level.txt
ocfworker-0.0.3.dist-info/RECORD
